bignumx/__init__.py
bignumx/big.py
bignumx-1.0.0.dist-info/licenses/LICENSE
bignumx-1.0.0.dist-info/METADATA
bignumx-1.0.0.dist-info/WHEEL
bignumx-1.0.0.dist-info/top_level.txt
bignumx-1.0.0.dist-info/RECORD
