Metadata-Version: 2.4
Name: bignumx
Version: 1.0.0
Summary: A small, easy-to-use wrapper around Python's Decimal with configurable precision and rounding.
Author: Jack
License: MIT
Project-URL: Homepage, https://github.com/jackdolan/bignumx
Project-URL: Source, https://github.com/jackdolan/bignumx
Project-URL: Issues, https://github.com/jackdolan/bignumx/issues
Requires-Python: >=3.7
License-File: LICENSE
Provides-Extra: dev
Requires-Dist: pytest; extra == "dev"
Requires-Dist: build; extra == "dev"
Requires-Dist: twine; extra == "dev"
Dynamic: license-file
